sniplates/__init__.py
sniplates/templates/sniplates/django.html
sniplates/templatetags/__init__.py
sniplates/templatetags/sniplates.py
django_sniplates-0.7.2.dist-info/LICENSE
django_sniplates-0.7.2.dist-info/METADATA
django_sniplates-0.7.2.dist-info/WHEEL
django_sniplates-0.7.2.dist-info/top_level.txt
django_sniplates-0.7.2.dist-info/RECORD
