Metadata-Version: 2.1
Name: django-sniplates
Version: 0.7.2
Summary: Efficient template macro sets for Django
Author-email: Curtis Maloney <curtis@tinbrain.net>
License: The MIT License (MIT)
Project-URL: Repository, https://github.com/funkybob/django-sniplates
Project-URL: Documentation, https://sniplates.readthedocs.io/en/latest/
Keywords: django,templates,forms
Classifier: Environment :: Web Environment
Classifier: Framework :: Django
Classifier: Framework :: Django :: 2.2
Classifier: Framework :: Django :: 3
Classifier: Framework :: Django :: 4.0
Classifier: Framework :: Django :: 4.1
Classifier: Framework :: Django :: 4.2
Classifier: License :: OSI Approved :: BSD License
Classifier: Operating System :: OS Independent
Classifier: Programming Language :: Python
Classifier: Programming Language :: Python :: 3.8
Classifier: Programming Language :: Python :: 3.9
Classifier: Programming Language :: Python :: 3.10
Classifier: Programming Language :: Python :: 3.11
License-File: LICENSE
Requires-Dist: django >=3.0.5
Provides-Extra: test
Requires-Dist: isort ; extra == 'test'
Requires-Dist: pytest ; extra == 'test'
Requires-Dist: pytest-cov ; extra == 'test'
Requires-Dist: pytest-django ; extra == 'test'
Requires-Dist: pylint ; extra == 'test'
Requires-Dist: pylint-pytest ; extra == 'test'
